{"CG00000170":{"CG00000172":{"CG00000173":{"en":"Sport Teams","he":"קבוצות ספורט"},"courses":["03940900"],"en":"Sports Courses","he":"קורסי ספורט"},"CG00000174":{"en":"Choir / Orchestra","he":"מקהלה / תזמורת"},"CG00000175":{"en":"Free Electives","he":"בחירה חופשית"},"CG00000551":{"en":"Community Program","he":"תוכנית קהילתית"},"CG00009076":{"courses":["03240261","03240265","03240266","03240395","03240436","03240446","03240453","03240697","03240908","03240992","03250021","03250022"],"en":"Malag Courses","he":"קורסי מל\"ג"},"CG00010092":{"courses":["03240261","03240265","03240266","03240395","03240436","03240446","03240453","03240697","03240908","03240992","03250021","03250022"],"en":"Malag Courses","he":" קורסי מל\"ג"},"en":"All-Technion Electives","he":"בחירה כלל טכניונית"},"CG00000200":{"CG00000233":{"en":"Options","he":"אפשרויות"},"en":"Electronic Circuits & VLSI Sys. (Single)","he":"מעגלים אלקטרוניים ומערכות VLSI(יחיד)"},"CG00000209":{"en":"Special. for Honors Students Cluster","he":"מיוחד לאשכול סטודנטים מצטיינים"},"CG00000441":{"CG00000442":{"CG00000219":{"en":"Or","he":"או"},"en":"Options","he":"אפשרויות"},"en":"Micro- & Nanoelectronics (Single)","he":"מיקרו וננו-אלקטרוניקה (יחיד)"},"CG00000443":{"CG00000444":{"en":"Mandatory Options","he":"אפשרויות חובה"},"CG00000445":{"en":"Options","he":"אפשרויות"},"en":"Electromagnetics & Photonics (Single)","he":"אלקטרומגנטיקה ופוטוניקה (יחיד)"},"CG00000448":{"CG00000225":{"en":"Mandatory Options","he":"אפשרויות חובה"},"CG00000449":{"courses":["01340058"],"en":"Options","he":"אפשרויות"},"en":"Biological Signals & Systems (Single)","he":"אותות ומערכות ביולוגיות (יחיד)"},"CG00000455":{"CG00000239":{"en":"Mandatory Options","he":"אפשרויות חובה"},"CG00000466":{"CG00000473":{"en":"Or","he":"או"},"en":"Options","he":"אפשרויות"},"en":"Power & Grid Systems (Single)","he":"מערכות חשמל ורשת (יחיד)"},"CG00000458":{"CG00000459":{"CG00000247":{"en":"Or","he":"או"},"en":"Options","he":"אפשרויות"},"en":"Microelectr. and Nanoelectr. (Double)","he":"מיקרואלקטר. וננו -אלקטרוני. (כפול)"},"CG00000460":{"CG00000461":{"en":"Options","he":"אפשרויות"},"en":"Electromagnetics and Photonics (Double)","he":"אלקטרומגנטיקה ופוטוניקה (כפול)"},"CG00000465":{"en":"Signal & Image Processing (Single)","he":"עיבוד אות ותמונות (יחיד)"},"CG00000496":{"CG00000497":{"CG00000468":{"en":"Or","he":"או"},"en":"Options","he":"אפשרויות"},"en":"Computer Networks (Single)","he":"רשתות מחשבים (יחיד)"},"CG00000500":{"CG00000470":{"en":"Mandatory Options","he":"אפשרויות חובה"},"CG00000501":{"CG00000224":{"en":"Or","he":"או"},"en":"Options","he":"אפשרויות"},"en":"Computers (Single)","he":"מחשבים (יחיד)"},"CG00000502":{"CG00000453":{"en":"Mandatory Options","he":"אפשרויות חובה"},"CG00000503":{"CG00000472":{"en":"Or","he":"או"},"en":"Options","he":"אפשרויות"},"en":"Machine Learning & Intelli. Sys (Single)","he":"למידת מכונה (יחיד)"},"CG00000506":{"CG00000507":{"CG00000252":{"en":"Or","he":"או"},"en":"Options","he":"אפשרויות"},"en":"Computers (Double)","he":"מחשבים (כפול)"},"CG00000522":{"CG00000499":{"CG00000215":{"en":"Or","he":"או"},"en":"Options","he":"אפשרויות"},"en":"Control and Robotics (Single)","he":"שליטה ורובוטיקה (יחיד)"},"CG00000643":{"CG00000644":{"courses":["01140032"],"en":"Mandatory Options","he":"קורסי חובה"},"courses":["00440148","00440157","00440158","00440167","00440169","00440252","01040034","01040038","01040214","01040215","01040220","01140071","01140075","02340117"],"en":"Mandatory Courses","he":"קורסי חובה"},"CG00000645":{"CG00000216":{"en":"Mandatory Options","he":"אפשרויות חובה"},"CG00000646":{"en":"Options","he":"אפשרויות"},"en":"Com. Sys. & Information Theory (Single)","he":"מערכות תקשורת ותורת המידע (יחיד)"},"CG00000647":{"CG00000242":{"en":"Mandatory Options","he":"אפשרויות חובה"},"CG00000648":{"CG00000527":{"en":"OR","he":"או"},"en":"Options","he":"אפשרויות"},"en":"Quantum Technologies (Single)","he":"טכנולוגיות קוונטיות (יחיד)"},"CG00000649":{"CG00000244":{"en":"Mandatory Options","he":"אפשרויות חובה"},"CG00000650":{"en":"Options","he":"אפשרויות"},"en":"Commu. Systems and Info. Theory (Double)","he":"מערכות תקשורת ותורת המידע (כפול)"},"CG00000651":{"courses":["00460210"],"en":"Faculty Electives","he":"מקצועות בחירה פקולטיים"},"CG00009737":{"courses":["03240053"],"en":"Hebrew Courses List","he":"רשימת קורסי עברית"},"CG00010208":{"courses":["03240032","03240033"],"en":"English Requirements","he":"דרישות אנגלית"},"en":"B.SC. IN ELECTRICAL ENGINEERING","he":"מוסמך למדעים בהנדסת חשמל"}