{"name":"requirement","nested":[{"name":"CG00000170","nested":[{"name":"CG00000172","nested":[{"name":"CG00000173","nested":[],"en":"Sport Teams","he":"קבוצות ספורט"}],"courses":["03940900"],"en":"Sports Courses","he":"קורסי ספורט"},{"name":"CG00000174","nested":[],"en":"Choir / Orchestra","he":"מקהלה / תזמורת"},{"name":"CG00000175","nested":[],"en":"Free Electives","he":"בחירה חופשית"},{"name":"CG00000551","nested":[],"en":"Community Program","he":"תוכנית קהילתית"},{"name":"CG00009076","nested":[],"courses":["03240261","03240265","03240266","03240395","03240436","03240446","03240453","03240697","03240908","03240992","03250021","03250022"],"en":"Malag Courses","he":"קורסי מל\"ג"},{"name":"CG00010092","nested":[],"courses":["03240261","03240265","03240266","03240395","03240436","03240446","03240453","03240697","03240908","03240992","03250021","03250022"],"en":"Malag Courses","he":" קורסי מל\"ג"}],"en":"All-Technion Electives","he":"בחירה כלל טכניונית"},{"name":"CG00002132","nested":[],"en":"List 1 - Mathematical and Computational","he":"רשימה 1: כלים מתמטיים וחישוביים"},{"name":"CG00002136","nested":[{"name":"CG00002137","nested":[{"name":"CG00002140","nested":[],"en":"Options","he":"אפשרויות בחירה"}],"en":"List 1","he":"רשימה 1"},{"name":"CG00002138","nested":[{"name":"CG00002127","nested":[],"en":"Options","he":"אפשרויות בחירה"},{"name":"CG00002139","nested":[],"en":"Options","he":"אפשרויות בחירה"}],"en":"List 2","he":"רשימה 2"}],"en":"Bioligy Course List","he":"רשימת קורסים של ביולוגיה"},{"name":"CG00005663","nested":[{"name":"CG00010784","nested":[],"courses":["01140051","01140077"],"en":"Mandatory options 1","he":"בחירה חובה 1"},{"name":"CG00010785","nested":[],"courses":["01140052","01140078"],"en":"Mandatory options 2","he":"בחירה חובה 2"}],"courses":["01040019","01040041","01040043","01040131","01040228","01250101","01250801","01340058","02340128"],"en":"Mandatory","he":"מקצועות חובה"},{"name":"CG00005664","nested":[{"name":"CG00002134","nested":[],"en":"List 3 - Processes and technologies","he":"רשימה 3 - תהליכים וטכנולוגיות"},{"name":"CG00005665","nested":[],"en":"List 2 - Biomaterials","he":"רשימה 2 - ביו -חומרים"},{"name":"CG00005666","nested":[],"courses":["01140054"],"en":"List 4 - Complementary subjects in chemi","he":"רשימה 4 - מקצועות משלימים בכימיה"}],"en":"Chemical Engineering Course List","he":"רשימת קורסים להנדסה כימית"},{"name":"CG00009680","nested":[],"courses":["03240053"],"en":"Hebrew Courses List","he":"רשימת קורסי עברית"},{"name":"CG00010191","nested":[],"courses":["03240032","03240033"],"en":"English Requirements","he":"דרישות אנגלית"}],"en":"B.SC. IN BIOCHEMICAL ENGINEERING","he":"מוסמך למדעים בהנדסה ביוכימית"}