{"name":"requirement","nested":[{"name":"CG00000170","nested":[{"name":"CG00000172","nested":[{"name":"CG00000173","nested":[],"en":"Sport Teams","he":"קבוצות ספורט"}],"courses":["03940900"],"en":"Sports Courses","he":"קורסי ספורט"},{"name":"CG00000174","nested":[],"en":"Choir / Orchestra","he":"מקהלה / תזמורת"},{"name":"CG00000175","nested":[],"en":"Free Electives","he":"בחירה חופשית"},{"name":"CG00000551","nested":[],"en":"Community Program","he":"תוכנית קהילתית"},{"name":"CG00009076","nested":[],"courses":["03240261","03240265","03240266","03240395","03240436","03240446","03240453","03240697","03240908","03240992","03250021","03250022"],"en":"Malag Courses","he":"קורסי מל\"ג"},{"name":"CG00010092","nested":[],"courses":["03240261","03240265","03240266","03240395","03240436","03240446","03240453","03240697","03240908","03240992","03250021","03250022"],"en":"Malag Courses","he":" קורסי מל\"ג"}],"en":"All-Technion Electives","he":"בחירה כלל טכניונית"},{"name":"CG00003805","nested":[],"en":"Group 1 - Science and technology educati","he":"התמחות 1 - חינוך למדע וטכנולוגיה"},{"name":"CG00003806","nested":[{"name":"CG00003807","nested":[],"courses":["00440158","00440169"],"en":"Group 2 - Labs and projects","he":"התמחות 2 - מעבדות ופרויקטים"},{"name":"CG00003808","nested":[],"en":"Group 3 - Microelectronics and nanoelect","he":"התמחות 3 - מיקרואלקטרוניקה וננואלקטרוניק"},{"name":"CG00003809","nested":[],"courses":["00440148"],"en":"Group 4 - Electro-optical waves and opti","he":"התמחות 4 - גלים אלקטרואופטיקה ותקשורת או"},{"name":"CG00003810","nested":[],"courses":["00440148"],"en":"Group 5 - Communication waves","he":"התמחות 5 - גלי תקשורת"},{"name":"CG00003811","nested":[],"en":"Group 6 - Monitoring","he":"התמחות 6 - ניטור"},{"name":"CG00003812","nested":[],"en":"Group 7 - Computers and computer network","he":"התמחות 7 - מחשבים ורשתות מחשבים"},{"name":"CG00003813","nested":[],"en":"Group 8 - Signals and biological systems","he":"התמחות 8 - אותות ומערכות ביולוגיים"},{"name":"CG00003814","nested":[],"en":"Group 9 - Signal and image processing","he":"התמחות 9 - עיבוד אותות ותמונות"},{"name":"CG00003815","nested":[],"en":"Group 10 - Energy and supply systems","he":"התמחות 10 - מערכות אנרגיה ואספקה"}],"en":"Cluster Collection","he":"אוסף התמחויות"},{"name":"CG00005855","nested":[{"name":"CG00003803","nested":[],"en":"Mandatory options","he":"אפשרויות בחירה בחובה"},{"name":"CG00003804","nested":[],"en":"Mandatory options","he":"אפשרויות בחירה בחובה"}],"courses":["00440157","00440167","00440252","01040034","01140032","01140071","01140075","02340117"],"en":"Mandatory","he":"מקצועות חובה"},{"name":"CG00009805","nested":[],"courses":["03240053"],"en":"Hebrew Courses List","he":"רשימת קורסי עברית"},{"name":"CG00010221","nested":[],"courses":["03240032","03240033"],"en":"English Requirements","he":"דרישות אנגלית"}],"en":"B.SC. IN EDUCATION (ELECTRICAL TECHNOL)","he":"מוסמך למדעים בהוראה (אלקטרוניקה-חשמל)"}