{"name":"requirement","nested":[{"name":"CG00000170","nested":[{"name":"CG00000172","nested":[{"name":"CG00000173","nested":[],"en":"Sport Teams","he":"קבוצות ספורט"}],"courses":["03940900"],"en":"Sports Courses","he":"קורסי ספורט"},{"name":"CG00000174","nested":[],"en":"Choir / Orchestra","he":"מקהלה / תזמורת"},{"name":"CG00000175","nested":[],"en":"Free Electives","he":"בחירה חופשית"},{"name":"CG00000551","nested":[],"en":"Community Program","he":"תוכנית קהילתית"},{"name":"CG00009076","nested":[],"courses":["03240261","03240265","03240266","03240395","03240436","03240446","03240453","03240697","03240908","03240992","03250021","03250022"],"en":"Malag Courses","he":"קורסי מל\"ג"},{"name":"CG00010092","nested":[],"courses":["03240261","03240265","03240266","03240395","03240436","03240446","03240453","03240697","03240908","03240992","03250021","03250022"],"en":"Malag Courses","he":" קורסי מל\"ג"}],"en":"All-Technion Electives","he":"בחירה כלל טכניונית"},{"name":"CG00006045","nested":[{"name":"CG00006046","nested":[],"courses":["01040181"],"en":"Seminars","he":"Seminars"}],"en":"Faculty Electives","he":"Faculty Electives"},{"name":"CG00006047","nested":[],"courses":["01140021","01140035","01140086","02340128"],"en":"Mandatory","he":"מקצועות חובה"},{"name":"CG00006048","nested":[],"en":"List 1 Mathematics","he":"רשימה א"},{"name":"CG00006051","nested":[],"en":"List 2 Physics","he":"רשימה 2: פיזיקה"},{"name":"CG00006624","nested":[],"courses":["01140250"],"en":"Mandatory Option 1","he":"מקצועות בחירה 1 בחובה"},{"name":"CG00009914","nested":[],"courses":["03240053"],"en":"Hebrew Courses List","he":"רשימת קורסי עברית"},{"name":"CG00010108","nested":[],"courses":["03240032","03240033"],"en":"English Requirements","he":"דרישות אנגלית"}],"en":"B.SC. IN MATHEMATICS-PHYSICS","he":"בוגר למדעים במתמטיקה-פיזיקה"}