{"code":"01040022","median":67.6,"points":5,"name":"חשבון דיפרנציאלי ואינטגרלי 2מ'","connections":{"dependencies":[["01040042"],["01040036"],["01040041"],["01040018"],["01040012"]],"adjacent":[],"exclusive":[]},"about":"הערה: מקצועות מכילים: 104282 + 104281. וקטורים וגיאומטריה מרחבית. תכונות יסודיות של פונקציות ממשיות של כמה משתנים. חקירת פונקציות של כמה משתנים. פונקציות סתומות. אינטגרלים מרובים. אנליזה וקטורית. אינטגרלים קוויים ומשטחיים. הקורס נבדל מהקורס 104004 בהעמקה נוספת תיאורטית ויישומית כאחד.","tests":[{"year":2025,"monthIndex":1,"day":14},{"year":2025,"monthIndex":2,"day":12}],"seasons":["Winter"]}