{"code":"01340019","median":81.6,"points":2.5,"name":"מבוא לביוכימיה ואנזימולוגיה","connections":{"dependencies":[["01240114","01340058"],["01340127","01240114"],["01250011","01340058"],["01340058","01240120"]],"adjacent":[],"exclusive":[]},"about":"בסמסטר א' הקורס מיועד: להנדסה כימית, כימיה, מכונות, סביבה, ביו-רפואה בלבד. בסמסטר ב' הקורס מיועד: לביולוגיה ומסלוליה, הנדסת ביוטכנולוגיה ומזון והוראת המדעים בלבד. המבנה והתכונות של חומצות אמינו. תכונות כימיות ופיסיקאליות של פפטידים וחלבונים: מבנה ראשוני, שניוני ושלישוני. תהליך הקיפול של חלבונים ותפקוד של השפרונים. תכונות ייחודיות לחלבונים סיביים, מבניים וממברנאלים. בידוד והפרדה של חלבונים. מבנה רביעוני: המוגלובין כמודל לאינטראקציות קואופרטיביות. אנזימים, עקרונות הקטליזה האנזימתית, קואנזימים וקופקטורים, קינטיקה אנזימתית, מבנה האתר הפעיל ומנגנוני קטליזה נפוצים. בקרת פעולתם של אנזימים ומנגנוני עיכוב שונים. בקרה של אנזימים על ידי מודיפיקציות אחר-תרגומיות. מבוא למבנה ותפקוד של סוכרים וליפידים.","tests":[{"year":2025,"monthIndex":1,"day":20},{"year":2025,"monthIndex":2,"day":27}]}