{"code":"01340020","median":77.3,"points":3.5,"name":"גנטיקה כללית","connections":{"dependencies":[["01340058"],["01340127"]],"adjacent":[],"exclusive":[]},"about":"בסמסטר א' הקורס מיועד להנ.ביוטכנולוגיה ומזון והשאר על בסיס פנוי. בסמסטר ב' הקורס מיועד לביולוגיה ומסלוליה והוראת המדעים בלבד. נושאיהקורס: חוקי התורשה המנדליים והלא מנדליים, מהות הגן, ניתוח שושלות, התיאוריה הכרומוזומלית של ההורשה, קביעת מין, תאחיזה, שחלוף ושיטות למיפוי גנים באדם ובאורגניזמים שונים, מוטציות ושינויים במבנה הכרומוזומים ובמספרם, אינטראקציה בין גנים. הערה: הקורס פתוח לסטודנטים מפקולטות אחרות. ידרשו מקצועות קדם מקבילים בתאום עם מורה הקורס.","tests":[{"year":2025,"monthIndex":1,"day":23},{"year":2025,"monthIndex":2,"day":21}],"seasons":["Winter","Spring","Summer"]}