{"code":"044198","median":80,"points":3,"name":"44198 - מבוא לעבוד ספרתי של אותות","connections":{"dependencies":[["044130"],[],["044131"],[]],"adjacent":[],"exclusive":[]},"about":"דגימה ושחזור. התמרת פורייה דיסקרטית ( DFT ) קונבולוציה\nמעגלית. אלגוריתמים לחישוב יעיל של DFT. אנליזה ספקטרלית.\nמבוא לתכן מסננים ספרתיים. פאזה לינארית מוכללת.\nתכן מסננים בעלי תגובת הלם סופית ( FIR ).\nתכן מסננים אנלוגיים ומסננים ספרתיים בעלי תגובת הלם\nאינסופית ( IIR ). מערכות מרובות קצבים, דצימציה ואינטרפולציה.","tests":[{"year":2024,"monthIndex":8,"day":5},{"year":2024,"monthIndex":8,"day":30}]}