{"code":"044131","median":84.4,"points":5,"name":"44131 - אותות ומערכות","connections":{"dependencies":[["044105","104214"],["044105","104221","104223"],["044191"],["104122","104276","104285"],["114071"]],"adjacent":[],"exclusive":["044130","044195"]},"about":"1. אותות רציפים ובדידים - מושגים בסיסיים.\n2. מערכות רציפות בזמן ובדידות בזמן - מושגים בסיסיים.\n3. אנליזה של מערכת לינארית במישור הזמן.\n4. התמרת לפלס.\n5. התמרת פוריה ותגובת תדר. אפנון וריבוב.\n6. התמרת Z ותפקידה במערכות בדידות. משוואות הפרש.\n7. התמרת פוריה (רציפה) של אות בדיד ותגובת תדר של מערכת בדידה.\n8. תאור מערכות במרחב המצב.מידול מערכות פיסיקליות, לינאריזציה.\n9. יציבות של מערכות לינאריות וקבועות בזמן.\n10. מערכות משוב: תכונות בסיסיות, יציבות, בקרי PID.","tests":["2024-08-26T00:00:00.000Z","2024-09-25T00:00:00.000Z"]}