{"code":"046200","median":80.1,"points":3,"name":"46200 - עבוד ונתוח תמונות","connections":{"dependencies":[["044130"],["104034"],["044130"],["094412"],["044130"],["104222"],["044130"],["094411"],["044131"],["094411"],["044131"],["104222"],["044131"],["094412"],["044131"],["104034"]],"adjacent":[],"exclusive":["336027","236860","336207","099798"]},"about":"מבוא לראייה ולעבוד תמונות. אותות ומערכות ליניאריות בדו-מימד. דגימה\nושחזור של תמונות: דגימה אחידה, תופעת הקיפול בתמונות ( ALIASING ),\nדגימה על סריג כללי. קוונטיזציה: סקלרית, שיקולים חזותיים, קוונטיזצית\nצבע. שיפור תמונות: פעולות נקודה, עיצוב היסטוגרמה, סינון והחלקה, הדגשת\nשפות. שחזור תמונה: שחזור ML, שחזור MAP. התמרות דיסקרטיות בדו-מימד.\nייצוג וניתוח תמונות ברזולוציה משתנה. דחיסת תמונה: מושגים בסיסיים בתורת\nהאינפורמציה, יתירויות בתמונות, דחיסה משמרת, דחיסה לא משמרת. מבוא לראיה\nממוחשבת."}