{"code":"104002","median":74.8,"points":2.5,"name":"104002 - מושגי יסוד במתמטיקה","connections":{"dependencies":[],"adjacent":[],"exclusive":["044114","094345","094346","104290","234129","234293"]},"about":"קדם: בגרות במתמטיקה 5 יח\"ל עם ציון 70 ומעלה או ציון עובר\nבבחינת סיווג במתמטיקה. הקדם לא יופעל עבור סטודנטים הלומדים במסגרת\nאפיק המעבר המקוצר מלימודי חוץ בשנת הלימודים הנוכחית.\nלוחות אמת, טאוטולוגיות, קבוצות, פעולות בין קבוצות, הקשר לפעולות\nהלוגיות, קבוצת החזקה, יחסים, פונקציות - תכונות, הרכב, פונקציות\nהפוכות, תמורות - זוגיות ואיזוגיות, יחסי שקילות, יחסי סדר סופיים\nואינסופיים, קבוצות ניתנות להימנות, משפט קנטור, מספרים רציונליים ואי\nרציונליים, פיתוח עשרוני אינסופי כדוגמה לגבול, אינדוקציה, משפט הול,\nעקרון שובך היונים.","tests":[{"year":2024,"monthIndex":8,"day":10},{"year":2024,"monthIndex":9,"day":14}]}