{"code":"198000","points":4,"name":"198000 - שיטות אסימפטוטיות","connections":{"dependencies":[["104122"],["104215"],["104221"]],"adjacent":[],"exclusive":["198001","198002"]},"about":"פיתוחים אסימפטוטיים, תופעת סטוקס, תורת ההפרות, מאזן דומיננטי, פתרונות\nמקומיים של משוואות דיפרנציאליות רגילות, פיתוחים של אינטגרלים: הלמה של\nווטסון, שיטת לפלס, אינטגרל פורייה, שיטת הפאזה הסטציונרית, שיטת המורד\nהתלול, תרומות לא לוקליות, פתוחים אסימפטוטיים מתואמים: שכבות גבול, הסעה\nחלשה, סקלות מרובות: שיטת ליוביל-גרין, שיטת פואנקרה-לייטהיל, תהודה.\nתוצאות למידה: בסיום הקורס הסטודנט יהיה מסוגל לקבל קרובים באופן שיטתי.","tests":[]}