{"code":"234112","median":75.9,"points":4,"name":"234112 - מבוא למחשב - שפת סי","connections":{"dependencies":[],"adjacent":[],"exclusive":["234102","234104","234106","234109","234111","234114","234117","234126","234127","234128","234130","234221","035019","094704"]},"about":"מבנה המחשב. גישה אלגוריתמית לפתרון בעיות. מושגי יסוד ותכנות\nבשפת C. פיתוח תכניות מלמעלה למטה. תכנות מבני. בדיקה מלמטה\nלמעלה. ניפוי שגיאות. תכנון הדפסות ביקורת. מדדים ליעילות\nהאלגוריתם. בעיות במספרים ממשיים והתכנסות. בעיות במספרים\nשלמים. פעולות במערכים: מיון, חיפוש, מיזוג. רקורסיה אלמנטרית.","tests":[]}