{"code":"236310","points":3,"name":"236310 - תורת השפות הפורמליות","connections":{"dependencies":[["234129"],["236343"],["236343","236353"],[]],"adjacent":[],"exclusive":[]},"about":"דקדוקים ושפות פורמליות, היררכית השפות של חומסקי, דקדוקים\nמטיפוס 0, השפות הניתנות למניה רקורסיבית ומכונות טיורינג,\nשפות בעלות הקשר ואוטומטים חסומים לינארית, שפת חסרות\nהקשר - אפיונים, משפטי הומומורפיזם ותת משפחות, אוטומטי\nמחסנית - מודלים שונים, בעיות הכרעה ואי-הכרעה בשפות, תכונות\nסגירות, סיבוכיות זמן ומקום של מכונות טיורינג המזהות שפות,\nחסמים לסיבוכיות הזמן והמקום של משפחות שונות של השפות,\nסיבוכיות של בעיות שונות בתורת השפות.","tests":[]}