{"code":"236496","median":89.5,"points":3,"name":"236496 - הנדסה לאחור","connections":{"dependencies":[["046209"],["234123"]],"adjacent":["236350"],"exclusive":[]},"about":"מבוא. הנדסה לאחור של תוכנה: ניתוח סטטי. ניתוח דינמי. פעולת הדיבגר,\nBREAKPOINTS. הוקינג. הזרקת קוד, IAT, HOT PATCHING. מבנים שונים של\nיישומי הוקינג. חולשות ושימוש בהן. טיפול בחריגות. שפות מבוססות עצמים\nושפות קודי ביניים, JIT. טכניקות אנטי-רברסינג. הסוואות בנוזקה. התקפות\nערוצי צד. הנדסה לאחור של חומרה. המבחן הסופי יערך בשני חלקים בני 3\nשעות כ\"א מול מחשב.\nתוצאות למידה: בסיום הקורס הסטודנט: 1. יבין איך מבצעים הנדסה לאחור של\nתוכנה, ויוכל ליישם מגוון טכניקות להבנת פעולת התוכנה ולשינוי פעולתה.\n2. ידע טכניקות למניעת ביצוע הנדסה לאחור לתוכנה, ולהפרעה להנדסה לאחור.\n3. יכיר את רוחב התחום, כולל היישום לשפות השונות, התקפות ערוצי צד,\nוהנדסה לאחור של חומרה.","tests":[{"year":2024,"monthIndex":8,"day":18},{"year":2024,"monthIndex":9,"day":27}]}